gpt_bot/__init__.py
gpt_bot/__main__.py
gpt_bot/record.py
gpt_bot/speak.py
gpt_bot-0.0.3.dist-info/METADATA
gpt_bot-0.0.3.dist-info/WHEEL
gpt_bot-0.0.3.dist-info/top_level.txt
gpt_bot-0.0.3.dist-info/RECORD
