Metadata-Version: 2.1
Name: gpt-bot
Version: 0.0.3
Summary: GPT Commandline interface bot
Home-page: https://github.com/hzhangxyz/gpt-bot
Author: Hao Zhang
Author-email: zh970205@mail.ustc.edu.cn
License: GPLv3
Requires-Python: >=3.9
Requires-Dist: numpy
Requires-Dist: openai
Requires-Dist: prompt-toolkit
Requires-Dist: pyaudio
Requires-Dist: tiktoken
